[
    {
        "x": 1,
        "y": 1,
        "v": 1.0
    },
    {
        "x": 1,
        "y": 2,
        "v": 0.8145914718778116
    },
    {
        "x": 1,
        "y": 3,
        "v": 0.15159831076316063
    },
    {
        "x": 1,
        "y": 4,
        "v": 0.5979450124074971
    },
    {
        "x": 1,
        "y": 5,
        "v": 0.6603778567260341
    },
    {
        "x": 1,
        "y": 6,
        "v": 0.04827542560882741
    },
    {
        "x": 1,
        "y": 7,
        "v": 0.614372558581509
    },
    {
        "x": 1,
        "y": 8,
        "v": 0.7165471682584333
    },
    {
        "x": 1,
        "y": 9,
        "v": 0.583979244727708
    },
    {
        "x": 1,
        "y": 10,
        "v": 0.551256466436799
    },
    {
        "x": 2,
        "y": 1,
        "v": 0.8145914718778116
    },
    {
        "x": 2,
        "y": 2,
        "v": 1.0
    },
    {
        "x": 2,
        "y": 3,
        "v": 0.08882141935963399
    },
    {
        "x": 2,
        "y": 4,
        "v": 0.5744056403706055
    },
    {
        "x": 2,
        "y": 5,
        "v": 0.7497716632185969
    },
    {
        "x": 2,
        "y": 6,
        "v": 0.06027151828925565
    },
    {
        "x": 2,
        "y": 7,
        "v": 0.6905070664016677
    },
    {
        "x": 2,
        "y": 8,
        "v": 0.7964622215757294
    },
    {
        "x": 2,
        "y": 9,
        "v": 0.5544486168694559
    },
    {
        "x": 2,
        "y": 10,
        "v": 0.5725307251206548
    },
    {
        "x": 3,
        "y": 1,
        "v": 0.15159831076316063
    },
    {
        "x": 3,
        "y": 2,
        "v": 0.08882141935963399
    },
    {
        "x": 3,
        "y": 3,
        "v": 1.0
    },
    {
        "x": 3,
        "y": 4,
        "v": 0.08287380394675146
    },
    {
        "x": 3,
        "y": 5,
        "v": 0.027413994026975114
    },
    {
        "x": 3,
        "y": 6,
        "v": 0.24819116938478392
    },
    {
        "x": 3,
        "y": 7,
        "v": 0.10419590587663391
    },
    {
        "x": 3,
        "y": 8,
        "v": 0.06822284976806765
    },
    {
        "x": 3,
        "y": 9,
        "v": 0.08604268433824963
    },
    {
        "x": 3,
        "y": 10,
        "v": 0.02077892427115001
    },
    {
        "x": 4,
        "y": 1,
        "v": 0.5979450124074971
    },
    {
        "x": 4,
        "y": 2,
        "v": 0.5744056403706055
    },
    {
        "x": 4,
        "y": 3,
        "v": 0.08287380394675146
    },
    {
        "x": 4,
        "y": 4,
        "v": 1.0
    },
    {
        "x": 4,
        "y": 5,
        "v": 0.47215898752654695
    },
    {
        "x": 4,
        "y": 6,
        "v": 0.060003456522956786
    },
    {
        "x": 4,
        "y": 7,
        "v": 0.4653250801690801
    },
    {
        "x": 4,
        "y": 8,
        "v": 0.48836710798332694
    },
    {
        "x": 4,
        "y": 9,
        "v": 0.4867185717985653
    },
    {
        "x": 4,
        "y": 10,
        "v": 0.3679107910763281
    },
    {
        "x": 5,
        "y": 1,
        "v": 0.6603778567260341
    },
    {
        "x": 5,
        "y": 2,
        "v": 0.7497716632185969
    },
    {
        "x": 5,
        "y": 3,
        "v": 0.027413994026975114
    },
    {
        "x": 5,
        "y": 4,
        "v": 0.47215898752654695
    },
    {
        "x": 5,
        "y": 5,
        "v": 1.0
    },
    {
        "x": 5,
        "y": 6,
        "v": 0.003280375843995261
    },
    {
        "x": 5,
        "y": 7,
        "v": 0.7321222992119234
    },
    {
        "x": 5,
        "y": 8,
        "v": 0.779712390470714
    },
    {
        "x": 5,
        "y": 9,
        "v": 0.5361638610921781
    },
    {
        "x": 5,
        "y": 10,
        "v": 0.5816864712418254
    },
    {
        "x": 6,
        "y": 1,
        "v": 0.04827542560882741
    },
    {
        "x": 6,
        "y": 2,
        "v": 0.06027151828925565
    },
    {
        "x": 6,
        "y": 3,
        "v": 0.24819116938478392
    },
    {
        "x": 6,
        "y": 4,
        "v": 0.060003456522956786
    },
    {
        "x": 6,
        "y": 5,
        "v": 0.003280375843995261
    },
    {
        "x": 6,
        "y": 6,
        "v": 1.0
    },
    {
        "x": 6,
        "y": 7,
        "v": 0.05266438062730005
    },
    {
        "x": 6,
        "y": 8,
        "v": 0.07859732072865083
    },
    {
        "x": 6,
        "y": 9,
        "v": 0.051921696286917826
    },
    {
        "x": 6,
        "y": 10,
        "v": 0.03251498479335936
    },
    {
        "x": 7,
        "y": 1,
        "v": 0.614372558581509
    },
    {
        "x": 7,
        "y": 2,
        "v": 0.6905070664016677
    },
    {
        "x": 7,
        "y": 3,
        "v": 0.10419590587663391
    },
    {
        "x": 7,
        "y": 4,
        "v": 0.4653250801690801
    },
    {
        "x": 7,
        "y": 5,
        "v": 0.7321222992119234
    },
    {
        "x": 7,
        "y": 6,
        "v": 0.05266438062730005
    },
    {
        "x": 7,
        "y": 7,
        "v": 1.0
    },
    {
        "x": 7,
        "y": 8,
        "v": 0.7931649184920766
    },
    {
        "x": 7,
        "y": 9,
        "v": 0.5059822104505113
    },
    {
        "x": 7,
        "y": 10,
        "v": 0.47114105364234965
    },
    {
        "x": 8,
        "y": 1,
        "v": 0.7165471682584333
    },
    {
        "x": 8,
        "y": 2,
        "v": 0.7964622215757294
    },
    {
        "x": 8,
        "y": 3,
        "v": 0.06822284976806765
    },
    {
        "x": 8,
        "y": 4,
        "v": 0.48836710798332694
    },
    {
        "x": 8,
        "y": 5,
        "v": 0.779712390470714
    },
    {
        "x": 8,
        "y": 6,
        "v": 0.07859732072865083
    },
    {
        "x": 8,
        "y": 7,
        "v": 0.7931649184920766
    },
    {
        "x": 8,
        "y": 8,
        "v": 1.0
    },
    {
        "x": 8,
        "y": 9,
        "v": 0.5472996083385996
    },
    {
        "x": 8,
        "y": 10,
        "v": 0.5759857164902955
    },
    {
        "x": 9,
        "y": 1,
        "v": 0.583979244727708
    },
    {
        "x": 9,
        "y": 2,
        "v": 0.5544486168694559
    },
    {
        "x": 9,
        "y": 3,
        "v": 0.08604268433824963
    },
    {
        "x": 9,
        "y": 4,
        "v": 0.4867185717985653
    },
    {
        "x": 9,
        "y": 5,
        "v": 0.5361638610921781
    },
    {
        "x": 9,
        "y": 6,
        "v": 0.051921696286917826
    },
    {
        "x": 9,
        "y": 7,
        "v": 0.5059822104505113
    },
    {
        "x": 9,
        "y": 8,
        "v": 0.5472996083385996
    },
    {
        "x": 9,
        "y": 9,
        "v": 1.0
    },
    {
        "x": 9,
        "y": 10,
        "v": 0.4179496121891588
    },
    {
        "x": 10,
        "y": 1,
        "v": 0.551256466436799
    },
    {
        "x": 10,
        "y": 2,
        "v": 0.5725307251206548
    },
    {
        "x": 10,
        "y": 3,
        "v": 0.02077892427115001
    },
    {
        "x": 10,
        "y": 4,
        "v": 0.3679107910763281
    },
    {
        "x": 10,
        "y": 5,
        "v": 0.5816864712418254
    },
    {
        "x": 10,
        "y": 6,
        "v": 0.03251498479335936
    },
    {
        "x": 10,
        "y": 7,
        "v": 0.47114105364234965
    },
    {
        "x": 10,
        "y": 8,
        "v": 0.5759857164902955
    },
    {
        "x": 10,
        "y": 9,
        "v": 0.4179496121891588
    },
    {
        "x": 10,
        "y": 10,
        "v": 1.0
    }
]